windows_use/__init__.py
windows_use/agent/__init__.py
windows_use/agent/service.py
windows_use/agent/utils.py
windows_use/agent/views.py
windows_use/agent/desktop/__init__.py
windows_use/agent/desktop/config.py
windows_use/agent/desktop/service.py
windows_use/agent/desktop/views.py
windows_use/agent/prompt/action.md
windows_use/agent/prompt/answer.md
windows_use/agent/prompt/observation.md
windows_use/agent/prompt/previous_observation.md
windows_use/agent/prompt/service.py
windows_use/agent/prompt/system.md
windows_use/agent/prompt/system_flash.md
windows_use/agent/registry/service.py
windows_use/agent/registry/views.py
windows_use/agent/tools/__init__.py
windows_use/agent/tools/service.py
windows_use/agent/tools/views.py
windows_use/agent/tree/__init__.py
windows_use/agent/tree/cache_utils.py
windows_use/agent/tree/config.py
windows_use/agent/tree/service.py
windows_use/agent/tree/utils.py
windows_use/agent/tree/views.py
windows_use/agent/watchdog/__init__.py
windows_use/agent/watchdog/event_handlers.py
windows_use/agent/watchdog/service.py
windows_use/llms/__init__.py
windows_use/llms/anthropic.py
windows_use/llms/azure_openai.py
windows_use/llms/base.py
windows_use/llms/cerebras.py
windows_use/llms/google.py
windows_use/llms/groq.py
windows_use/llms/mistral.py
windows_use/llms/ollama.py
windows_use/llms/open_router.py
windows_use/llms/openai.py
windows_use/llms/views.py
windows_use/messages/__init__.py
windows_use/messages/service.py
windows_use/telemetry/service.py
windows_use/telemetry/views.py
windows_use/tool/__init__.py
windows_use/tool/service.py
windows_use/uia/__init__.py
windows_use/uia/controls.py
windows_use/uia/core.py
windows_use/uia/enums.py
windows_use/uia/events.py
windows_use/uia/patterns.py
windows_use/vdm/__init__.py
windows_use/vdm/core.py
windows_use-0.7.4.dist-info/METADATA
windows_use-0.7.4.dist-info/WHEEL
windows_use-0.7.4.dist-info/licenses/LICENSE
windows_use-0.7.4.dist-info/RECORD
