Metadata-Version: 2.4
Name: windows-use
Version: 0.7.4
Summary: An AI Agent that interacts with Windows OS at GUI level.
Project-URL: homepage, https://github.com/CursorTouch
Author-email: Jeomon George <jeogeoalukka@gmail.com>
License-Expression: MIT
License-File: LICENSE
Keywords: agent,ai,ai agent,automation,desktop,windows
Classifier: Development Status :: 4 - Beta
Classifier: Intended Audience :: Developers
Classifier: License :: OSI Approved :: MIT License
Classifier: Operating System :: Microsoft :: Windows
Classifier: Programming Language :: Python :: 3.13
Classifier: Topic :: Software Development :: Libraries :: Python Modules
Classifier: Topic :: Software Development :: User Interfaces
Requires-Python: >=3.13
Requires-Dist: anthropic>=0.68.1
Requires-Dist: cerebras-cloud-sdk>=1.50.1
Requires-Dist: comtypes>=1.4.14
Requires-Dist: fuzzywuzzy>=0.18.0
Requires-Dist: google-genai>=1.45.0
Requires-Dist: groq>=0.29.0
Requires-Dist: ipykernel>=6.29.5
Requires-Dist: markdownify>=1.1.0
Requires-Dist: mistralai>=1.9.11
Requires-Dist: ollama>=0.5.1
Requires-Dist: openai>=1.93.0
Requires-Dist: pillow>=11.2.1
Requires-Dist: posthog>=6.7.8
Requires-Dist: psutil>=7.0.0
Requires-Dist: pyautogui>=0.9.54
Requires-Dist: pydantic>=2.11.7
Requires-Dist: python-dotenv>=1.0.0
Requires-Dist: python-levenshtein>=0.27.1
Requires-Dist: pywin32>=311
Requires-Dist: rich>=14.0.0
Requires-Dist: tabulate>=0.9.0
Requires-Dist: termcolor>=3.1.0
Requires-Dist: twine>=6.1.0
Requires-Dist: uuid7>=0.1.0
Provides-Extra: dev
Requires-Dist: pytest>=8.4.1; extra == 'dev'
Requires-Dist: ruff>=0.12.1; extra == 'dev'
